LICENSE
p115updatedb/__init__.py
p115updatedb/__main__.py
p115updatedb/init-with-event.sql
p115updatedb/init-without-event.sql
p115updatedb/init.sql
p115updatedb/py.typed
p115updatedb/query.py
p115updatedb/updatedb.py
p115updatedb-0.0.12.2.dist-info/LICENSE
p115updatedb-0.0.12.2.dist-info/LICENSE_zh
p115updatedb-0.0.12.2.dist-info/METADATA
p115updatedb-0.0.12.2.dist-info/WHEEL
p115updatedb-0.0.12.2.dist-info/entry_points.txt
p115updatedb-0.0.12.2.dist-info/RECORD
